{
  "run_at": "2026-06-03T04:00:00Z",
  "run_type": "evening",
  "market_pulse": "Competitors ramping summer programming with high-profile DJs (Steve Aoki, DJ Pauly D, RL Grime); LIV EDC momentum cooling post-event.",
  "urgent_alert_count": 0,
  "weekend_readiness": null,
  "content_gaps": [
    {
      "gap_type": "summer_countdown_content",
      "description": "Competitors using Instagram countdown stickers and Story series for weekend events; LIV minimal Story activity detected",
      "competitors_doing_it": ["Zouk Nightclub", "OMNIA Nightclub", "Encore Beach Club"],
      "urgency": "high",
      "suggested_action": "Launch 48-hour countdown Story series for upcoming weekend headliner"
    },
    {
      "gap_type": "user_generated_content_hashtag",
      "description": "#EDCWeek and #VegasParty trending; competitors pushing UGC contests, LIV relying on organic mentions",
      "competitors_doing_it": ["Zouk Nightclub", "Encore Beach Club", "OMNIA Nightclub"],
      "urgency": "medium",
      "suggested_action": "Run hashtag contest with guestlist prizes to boost UGC engagement"
    },
    {
      "gap_type": "tiktok_trending_sounds",
      "description": "Beach club UGC leveraging trending sounds (#discolines, @discolines collab); LIV content appears more static",
      "competitors_doing_it": ["Encore Beach Club", "Palm Tree Beach Club"],
      "urgency": "medium",
      "suggested_action": "Partner with @discolines or equivalent micro-creator for LIV beach content series"
    }
  ],
  "influencer_activity": [
    {
      "handle": "@discolines",
      "platform": "TT",
      "mention": "Created #discolines content trend at LIV Beach and Encore; high engagement with pool/nightlife clips",
      "posts_found": 3,
      "engagement_level": "High"
    },
    {
      "handle": "@viphostvegas",
      "platform": "TT",
      "mention": "VIP promoter content driving traffic to multiple venues; EDC Week focus pulling audience away post-event",
      "posts_found": 2,
      "engagement_level": "High"
    }
  ],
  "liv_outreach_targets": [
    {
      "creator": "@discolines",
      "platform": "TT",
      "reason": "Trending beach club content, high engagement, already featured LIV Beach",
      "suggested_collab": "Sponsored story series or content creator pass"
    }
  ],
  "story_activity": [
    {
      "venue": "OMNIA Nightclub",
      "content_type": "announcement",
      "summary": "Steve Aoki and DJ Pauly D announcements for June 19-20",
      "detected_at": "2026-06-02T23:00:00Z",
      "urgency": true
    },
    {
      "venue": "Zouk Nightclub",
      "content_type": "announcement",
      "summary": "RL Grime (June 6) and BOLO (June 5) THE PIT series activation",
      "detected_at": "2026-06-02T22:30:00Z",
      "urgency": true
    },
    {
      "venue": "Encore Beach Club",
      "content_type": "countdown",
      "summary": "Marshmello (5/30), Acraze (5/29), DJ Vice (5/27) lineup posted",
      "detected_at": "2026-06-01T12:00:00Z",
      "urgency": false
    }
  ],
  "venues": [
    {
      "venue": "LIV Nightclub (@livnightclub)",
      "posts_found": 2,
      "urgent": false,
      "summary": "EDC Week momentum fading; limited new content since May 26 peak activity",
      "flags": [],
      "raw_posts": [
        {
          "platform": "TT",
          "content_summary": "EDC Week coverage - LIV Las Vegas EDC Week activity, user outfit/vibe posts featuring venue",
          "posted_at": "2026-05-26",
          "engagement_note": "High",
          "flags": []
        },
        {
          "platform": "IG",
          "content_summary": "Event lineup page updated with summer schedule reference",
          "posted_at": "2026-05-03",
          "engagement_note": "Normal",
          "flags": []
        }
      ]
    },
    {
      "venue": "LIV Beach (@livbeachlasvegas)",
      "posts_found": 2,
      "urgent": false,
      "summary": "User-generated content picking up; John Summit mentions; VIP promoter activity visible",
      "flags": ["talent_announcement"],
      "raw_posts": [
        {
          "platform": "TT",
          "content_summary": "Day 2 spring break outfit content featuring John Summit headliner at LIV Beach",
          "posted_at": "2026-05-20",
          "engagement_note": "High",
          "flags": []
        },
        {
          "platform": "TT",
          "content_summary": "VIP promoter content - private cabanas, bottle service, John Summit meet-and-greet",
          "posted_at": "2026-05-28",
          "engagement_note": "High",
          "flags": ["promo_offer"]
        }
      ]
    },
    {
      "venue": "XS Nightclub",
      "posts_found": 0,
      "urgent": false,
      "summary": "Limited social media detection; event calendar active but no viral social content found",
      "flags": [],
      "raw_posts": []
    },
    {
      "venue": "Encore Beach Club",
      "posts_found": 1,
      "urgent": false,
      "summary": "Heavy May weekend DJ lineup with Marshmello, Acraze, Subtronics; Instagram bio updated with confirmed dates",
      "flags": ["talent_announcement"],
      "raw_posts": [
        {
          "platform": "IG",
          "content_summary": "Bio update with confirmed DJ lineup: DJ Vice (5/27), Acraze (5/29), Marshmello (5/30), Subtronics (5/30), Alec Monopoly (5/31)",
          "posted_at": "2026-05-27",
          "engagement_note": "High",
          "flags": ["talent_announcement"]
        }
      ]
    },
    {
      "venue": "OMNIA Nightclub",
      "posts_found": 2,
      "urgent": true,
      "summary": "June talent announcement: Steve Aoki (June 19) and DJ Pauly D (June 20) confirmed",
      "flags": ["talent_announcement"],
      "raw_posts": [
        {
          "platform": "Ticket/Eventbrite",
          "content_summary": "Steve Aoki performance announced for Friday, June 19, 2026",
          "posted_at": "2026-06-02",
          "engagement_note": "High",
          "flags": ["talent_announcement"]
        },
        {
          "platform": "Ticket/Eventbrite",
          "content_summary": "DJ Pauly D performance announced for Saturday, June 20, 2026",
          "posted_at": "2026-06-02",
          "engagement_note": "High",
          "flags": ["talent_announcement"]
        }
      ]
    },
    {
      "venue": "Omnia Beach Club",
      "posts_found": 0,
      "urgent": false,
      "summary": "No recent social media activity detected; venue operating under Tao Group umbrella with shared promotion",
      "flags": [],
      "raw_posts": []
    },
    {
      "venue": "Zouk Nightclub",
      "posts_found": 3,
      "urgent": true,
      "summary": "THE PIT series launching with heavy hitters: BOLO (June 5), RL Grime (June 6), Meduza (May 30)",
      "flags": ["talent_announcement"],
      "raw_posts": [
        {
          "platform": "IG",
          "content_summary": "THE PIT series announcement: BOLO and RL Grime confirmed for early June dates",
          "posted_at": "2026-06-01",
          "engagement_note": "High",
          "flags": ["talent_announcement"]
        },
        {
          "platform": "IG",
          "content_summary": "Meduza performance (May 30) and upcoming THE PIT events posted by @zoukgrouplv",
          "posted_at": "2026-05-30",
          "engagement_note": "High",
          "flags": ["talent_announcement"]
        },
        {
          "platform": "TT",
          "content_summary": "User-generated content from Meduza event and upcoming Zouk nightlife",
          "posted_at": "2026-05-30",
          "engagement_note": "Normal",
          "flags": []
        }
      ]
    },
    {
      "venue": "Hakkasan Nightclub",
      "posts_found": 1,
      "urgent": false,
      "summary": "Major talent bookings visible (Steve Aoki, DJ Drama, TWINSICK); limited recent social posting",
      "flags": ["talent_announcement"],
      "raw_posts": [
        {
          "platform": "Ticket/Eventbrite",
          "content_summary": "2026-2027 packed schedule with Steve Aoki, DJ Drama, TWINSICK performances available for booking",
          "posted_at": "2026-03-15",
          "engagement_note": "Normal",
          "flags": ["talent_announcement"]
        }
      ]
    },
    {
      "venue": "Palm Tree Beach Club",
      "posts_found": 2,
      "urgent": false,
      "summary": "Recent DJ lineup active with Benny Benassi and Louis the Child weekend bookings; 233K Instagram followers",
      "flags": ["talent_announcement"],
      "raw_posts": [
        {
          "platform": "IG",
          "content_summary": "Weekend lineup: Benny Benassi (Saturday), Louis the Child (Sunday) announced",
          "posted_at": "2026-06-01",
          "engagement_note": "High",
          "flags": ["talent_announcement"]
        },
        {
          "platform": "IG",
          "content_summary": "Luxury daylife positioning with Tao Group partnership messaging",
          "posted_at": "2026-05-25",
          "engagement_note": "Normal",
          "flags": []
        }
      ]
    },
    {
      "venue": "Tao Beach (The Venetian)",
      "posts_found": 1,
      "urgent": false,
      "summary": "Confirmed June 8 Tiësto pool party and June 21 DJ Sourmilk event; summer programming active",
      "flags": ["talent_announcement"],
      "raw_posts": [
        {
          "platform": "Ticket/Eventbrite",
          "content_summary": "Tiësto live pool party June 8 at 11am and DJ Sourmilk June 21 confirmed",
          "posted_at": "2026-06-02",
          "engagement_note": "High",
          "flags": ["talent_announcement"]
        }
      ]
    }
  ]
}
